DecryptLogin/__init__.py
DecryptLogin/login.py
DecryptLogin/modules/__init__.py
DecryptLogin/modules/clients/QQId.py
DecryptLogin/modules/clients/QQQun.py
DecryptLogin/modules/clients/QQZone.py
DecryptLogin/modules/clients/__init__.py
DecryptLogin/modules/clients/alipan.py
DecryptLogin/modules/clients/baidu.py
DecryptLogin/modules/clients/baidupan.py
DecryptLogin/modules/clients/baidutieba.py
DecryptLogin/modules/clients/baseclient.py
DecryptLogin/modules/clients/bilibili.py
DecryptLogin/modules/clients/cloud189.py
DecryptLogin/modules/clients/codalab.py
DecryptLogin/modules/clients/dazhongdianping.py
DecryptLogin/modules/clients/douban.py
DecryptLogin/modules/clients/douyu.py
DecryptLogin/modules/clients/eSurfing.py
DecryptLogin/modules/clients/fishc.py
DecryptLogin/modules/clients/github.py
DecryptLogin/modules/clients/icourse163.py
DecryptLogin/modules/clients/ifeng.py
DecryptLogin/modules/clients/jianguoyun.py
DecryptLogin/modules/clients/jingdong.py
DecryptLogin/modules/clients/lagou.py
DecryptLogin/modules/clients/mieshop.py
DecryptLogin/modules/clients/migu.py
DecryptLogin/modules/clients/mpweixin.py
DecryptLogin/modules/clients/music163.py
DecryptLogin/modules/clients/pypi.py
DecryptLogin/modules/clients/qqmusic.py
DecryptLogin/modules/clients/qunar.py
DecryptLogin/modules/clients/renren.py
DecryptLogin/modules/clients/sohu.py
DecryptLogin/modules/clients/stackoverflow.py
DecryptLogin/modules/clients/taobao.py
DecryptLogin/modules/clients/tencentvideo.py
DecryptLogin/modules/clients/toutiao.py
DecryptLogin/modules/clients/twitter.py
DecryptLogin/modules/clients/w3cschool.py
DecryptLogin/modules/clients/weibo.py
DecryptLogin/modules/clients/xiaomihealth.py
DecryptLogin/modules/clients/ximalaya.py
DecryptLogin/modules/clients/youdao.py
DecryptLogin/modules/clients/zgconline.py
DecryptLogin/modules/clients/zhihu.py
DecryptLogin/modules/clients/zt12306.py
DecryptLogin/modules/core/QQId.py
DecryptLogin/modules/core/QQQun.py
DecryptLogin/modules/core/QQZone.py
DecryptLogin-0.3.9.dist-info/LICENSE
DecryptLogin-0.3.9.dist-info/METADATA
DecryptLogin-0.3.9.dist-info/WHEEL
DecryptLogin-0.3.9.dist-info/top_level.txt
DecryptLogin-0.3.9.dist-info/zip-safe
DecryptLogin-0.3.9.dist-info/RECORD
