Metadata-Version: 2.1
Name: DecryptLogin
Version: 0.3.9
Summary: DecryptLogin: APIs for loginning some websites by using requests.
Home-page: https://github.com/CharlesPikachu/DecryptLogin
Author: Charles
Author-email: charlesblwx@gmail.com
License: Apache License 2.0
Platform: UNKNOWN
Classifier: License :: OSI Approved :: Apache Software License
Classifier: Programming Language :: Python :: 3
Classifier: Intended Audience :: Developers
Classifier: Operating System :: OS Independent
License-File: LICENSE
Requires-Dist: rsa (>=4.0)
Requires-Dist: qrcode (>=6.1)
Requires-Dist: pillow (>=6.0.0)
Requires-Dist: PyExecJS (>=1.5.1)
Requires-Dist: requests (>=2.22.0)
Requires-Dist: pycryptodome (>=3.8.1)
Requires-Dist: requests-toolbelt (>=0.9.1)
Requires-Dist: gmssl (>=3.2.1)
